LICENSE
README.md
setup.py
gptsubtitler/__init__.py
gptsubtitler/cli.py
gptsubtitler/transcriber.py
gptsubtitler/translator.py
gptsubtitler/video_utils.py
gptsubtitler.egg-info/PKG-INFO
gptsubtitler.egg-info/SOURCES.txt
gptsubtitler.egg-info/dependency_links.txt
gptsubtitler.egg-info/entry_points.txt
gptsubtitler.egg-info/requires.txt
gptsubtitler.egg-info/top_level.txt