Metadata-Version: 2.1
Name: gptsubtitler
Version: 0.0.10
Summary: Automatically subtitle any video spoken in any language to a language of your choice.
Author: extremq
Author-email: extremqcontact@gmail.com
Classifier: License :: OSI Approved :: MIT License
Classifier: Operating System :: OS Independent
License-File: LICENSE
